fastapi_init/__init__.py
fastapi_init/cli.py
fastapi_start_project-0.1.0.dist-info/licenses/LICENCE
fastapi_start_project-0.1.0.dist-info/METADATA
fastapi_start_project-0.1.0.dist-info/WHEEL
fastapi_start_project-0.1.0.dist-info/entry_points.txt
fastapi_start_project-0.1.0.dist-info/top_level.txt
fastapi_start_project-0.1.0.dist-info/RECORD
