Metadata-Version: 2.4
Name: fastapi-start-project
Version: 0.1.0
Summary: Inicializador de proyectos FastAPI con entorno virtual, Docker y más
Author-email: Edier <edierguerra55@gmail.com>
License-Expression: MIT
Requires-Python: >=3.8
License-File: LICENCE
Dynamic: license-file
